{"version": 0.6, "generator": "Overpass API 0.7.61.5 4133829e", "osm3s": {"timestamp_osm_base": "2023-12-06T15:06:04Z", "copyright": "The data included in this document is from www.openstreetmap.org. The data is made available under ODbL."}, "elements": [{"type": "node", "id": 1837558335, "lat": -34.082117, "lon": 138.7804871}, {"type": "node", "id": 1837558349, "lat": -34.087178, "lon": 138.7767042}, {"type": "node", "id": 1837558367, "lat": -34.0836086, "lon": 138.7799497}, {"type": "node", "id": 1837558388, "lat": -34.0843269, "lon": 138.7793814}, {"type": "node", "id": 1837558394, "lat": -34.0792007, "lon": 138.7817192}, {"type": "node", "id": 1837558426, "lat": -34.087937, "lon": 138.7760473}, {"type": "node", "id": 1837558523, "lat": -34.0809535, "lon": 138.7807607}, {"type": "node", "id": 1837558530, "lat": -34.0830095, "lon": 138.7802312}, {"type": "node", "id": 1837558548, "lat": -34.0798909, "lon": 138.7812608}, {"type": "node", "id": 1886648897, "lat": -34.0827752, "lon": 138.7803093}, {"type": "node", "id": 1886648898, "lat": -34.087419, "lon": 138.7861689}, {"type": "node", "id": 1886648899, "lat": -34.0888512, "lon": 138.7879924}, {"type": "node", "id": 1886648900, "lat": -34.0891695, "lon": 138.7883806}, {"type": "node", "id": 1928786214, "lat": -34.077055, "lon": 138.784195}, {"type": "node", "id": 1930509505, "lat": -34.0777311, "lon": 138.783374}, {"type": "node", "id": 1930509509, "lat": -34.0780762, "lon": 138.7829549}, {"type": "node", "id": 1930509576, "lat": -34.0785887, "lon": 138.7823322}, {"type": "node", "id": 1930509599, "lat": -34.0788682, "lon": 138.7820148}, {"type": "node", "id": 1930509601, "lat": -34.0789217, "lon": 138.7819672}, {"type": "node", "id": 1930509616, "lat": -34.0795205, "lon": 138.7814884}, {"type": "node", "id": 1930509637, "lat": -34.0803174, "lon": 138.7810165}, {"type": "node", "id": 1930509642, "lat": -34.0804518, "lon": 138.7809504}, {"type": "node", "id": 1930509648, "lat": -34.080587, "lon": 138.7808839}, {"type": "node", "id": 1930509675, "lat": -34.0811314, "lon": 138.7807189}, {"type": "node", "id": 1930509746, "lat": -34.0832999, "lon": 138.7801168}, {"type": "node", "id": 1930509765, "lat": -34.0838282, "lon": 138.7797808}, {"type": "node", "id": 1930509768, "lat": -34.083962, "lon": 138.7796869}, {"type": "node", "id": 1930509833, "lat": -34.084124, "lon": 138.7820048}, {"type": "node", "id": 1930509837, "lat": -34.084291, "lon": 138.7822219}, {"type": "node", "id": 1930509850, "lat": -34.0847839, "lon": 138.7828439}, {"type": "node", "id": 1930509875, "lat": -34.0852065, "lon": 138.7833905}, {"type": "node", "id": 1930509877, "lat": -34.0852157, "lon": 138.7785775}, {"type": "node", "id": 1930509885, "lat": -34.0853372, "lon": 138.7835534}, {"type": "node", "id": 1930509897, "lat": -34.0856881, "lon": 138.7781372}, {"type": "node", "id": 1930509906, "lat": -34.0859099, "lon": 138.7842647}, {"type": "node", "id": 1930509940, "lat": -34.0866507, "lon": 138.7772013}, {"type": "node", "id": 1930509965, "lat": -34.0875934, "lon": 138.7763153}, {"type": "node", "id": 1930509985, "lat": -34.0882578, "lon": 138.7758346}, {"type": "node", "id": 1932198612, "lat": -34.0874503, "lon": 138.7764497}, {"type": "node", "id": 2712230189, "lat": -34.0861286, "lon": 138.7845407}, {"type": "node", "id": 3820044244, "lat": -34.0872713, "lon": 138.7859825}, {"type": "node", "id": 5064023865, "lat": -34.088513, "lon": 138.7757273}, {"type": "node", "id": 6007271718, "lat": -34.0864623, "lon": 138.7849614}, {"type": "node", "id": 7430520511, "lat": -34.0834511, "lon": 138.7811622}, {"type": "node", "id": 9401982534, "lat": -34.0859766, "lon": 138.7843489, "tags": {"railway": "level_crossing"}}, {"type": "way", "id": 182693540, "nodes": [1930509648, 1930509642, 1930509637, 1837558548, 1930509616, 1837558394, 1930509601, 1930509599, 1930509576, 1930509509, 1930509505, 1928786214], "tags": {"highway": "trunk", "name": "Burra Road", "network": "AU:SA;AU:SA", "ref": "A32;B84", "source": "survey", "source:name": "Data.sa.gov.au", "surface": "asphalt"}}, {"type": "way", "id": 182693544, "nodes": [7430520511, 1886648897], "tags": {"highway": "primary", "maxspeed": "50", "name": "Belvidere Road", "network": "AU:SA", "oneway": "no", "ref": "B84", "source": "GPS", "surface": "asphalt"}}, {"type": "way", "id": 295458636, "nodes": [1886648900, 1886648899, 1886648898, 3820044244, 6007271718, 2712230189, 9401982534, 1930509906], "tags": {"highway": "primary", "maxspeed": "50", "name": "Marrabel Road", "network": "AU:SA", "oneway": "no", "ref": "B84", "source": "GPS", "surface": "asphalt"}}, {"type": "way", "id": 425424761, "nodes": [1837558523, 1930509648], "tags": {"bridge": "yes", "highway": "trunk", "layer": "1", "maxspeed": "60", "name": "Burra Road", "network": "AU:SA;AU:SA", "ref": "A32;B84", "source": "survey", "surface": "asphalt"}}, {"type": "way", "id": 425424762, "nodes": [1886648897, 1837558335, 1930509675, 1837558523], "tags": {"highway": "trunk", "maxspeed": "60", "name": "Burra Road", "network": "AU:SA;AU:SA", "ref": "A32;B84", "source": "survey", "source:name": "Data.sa.gov.au", "surface": "asphalt"}}, {"type": "way", "id": 519311693, "nodes": [5064023865, 1930509985, 1837558426, 1930509965, 1932198612, 1837558349], "tags": {"highway": "trunk", "maxspeed": "80", "name": "Burra Road", "network": "AU:SA", "oneway": "no", "ref": "A32", "source": "survey", "source:name": "Data.sa.gov.au", "surface": "asphalt"}}, {"type": "way", "id": 519311698, "nodes": [1930509746, 1837558530, 1886648897], "tags": {"highway": "trunk", "maxspeed": "60", "name": "Burra Road", "network": "AU:SA", "oneway": "no", "ref": "A32", "source": "survey", "source:name": "Data.sa.gov.au", "surface": "asphalt"}}, {"type": "way", "id": 794436384, "nodes": [1930509906, 1930509885, 1930509875, 1930509850, 1930509837, 1930509833, 7430520511], "tags": {"highway": "primary", "maxspeed": "50", "name": "Belvidere Road", "network": "AU:SA", "oneway": "no", "ref": "B84", "source": "GPS", "surface": "asphalt"}}, {"type": "way", "id": 794436385, "nodes": [1837558349, 1930509940, 1930509897, 1930509877, 1837558388, 1930509768, 1930509765, 1837558367, 1930509746], "tags": {"highway": "trunk", "maxspeed": "60", "name": "Burra Road", "network": "AU:SA", "oneway": "no", "ref": "A32", "source": "survey", "source:name": "Data.sa.gov.au", "surface": "asphalt"}}]}