[{"place_id": 11443594, "licence": "Data \u00a9 OpenStreetMap contributors, ODbL 1.0. http://osm.org/copyright", "osm_type": "node", "osm_id": 9740460581, "lat": "41.681163", "lon": "-72.7382314", "class": "place", "type": "house", "place_rank": 30, "importance": 9.99999999995449e-06, "addresstype": "place", "name": "", "display_name": "16, Johnson Street, Elm Hill, Newington, Capitol Planning Region, Connecticut, 06111, United States", "boundingbox": ["41.6811130", "41.6812130", "-72.7382814", "-72.7381814"]}]