{"version": 0.6, "generator": "Overpass API 0.7.61.5 4133829e", "osm3s": {"timestamp_osm_base": "2023-12-06T09:27:36Z", "copyright": "The data included in this document is from www.openstreetmap.org. The data is made available under ODbL."}, "elements": [{"type": "node", "id": 21401208, "lat": -33.7105177, "lon": 151.294234}, {"type": "node", "id": 21401209, "lat": -33.7105831, "lon": 151.293488}, {"type": "node", "id": 21401211, "lat": -33.7099264, "lon": 151.2958017}, {"type": "node", "id": 26381271, "lat": -33.7108624, "lon": 151.2904379}, {"type": "node", "id": 26381272, "lat": -33.7110264, "lon": 151.2917708}, {"type": "node", "id": 26381274, "lat": -33.7109282, "lon": 151.2924757}, {"type": "node", "id": 26381638, "lat": -33.7102071, "lon": 151.2953091}, {"type": "node", "id": 26381649, "lat": -33.7093604, "lon": 151.2959847}, {"type": "node", "id": 26381650, "lat": -33.7090299, "lon": 151.296099}, {"type": "node", "id": 29612711, "lat": -33.705135, "lon": 151.2974069, "tags": {"highway": "traffic_signals"}}, {"type": "node", "id": 29699074, "lat": -33.7037632, "lon": 151.2976175}, {"type": "node", "id": 60570377, "lat": -33.7027525, "lon": 151.2978747}, {"type": "node", "id": 60570416, "lat": -33.7035882, "lon": 151.297567}, {"type": "node", "id": 60570649, "lat": -33.7019085, "lon": 151.298596, "tags": {"highway": "traffic_signals"}}, {"type": "node", "id": 60570650, "lat": -33.702977, "lon": 151.2978461}, {"type": "node", "id": 60570651, "lat": -33.703598, "lon": 151.2976443}, {"type": "node", "id": 152289351, "lat": -33.7106041, "lon": 151.2896274}, {"type": "node", "id": 152296038, "lat": -33.7072157, "lon": 151.296883}, {"type": "node", "id": 152298685, "lat": -33.7050938, "lon": 151.2973044, "tags": {"highway": "traffic_signals"}}, {"type": "node", "id": 152301256, "lat": -33.7104083, "lon": 151.2940671}, {"type": "node", "id": 152302463, "lat": -33.703753, "lon": 151.2975374}, {"type": "node", "id": 152303284, "lat": -33.7071943, "lon": 151.2967868}, {"type": "node", "id": 152307818, "lat": -33.7081112, "lon": 151.2965348}, {"type": "node", "id": 152311447, "lat": -33.7078272, "lon": 151.2965375, "tags": {"highway": "traffic_signals"}}, {"type": "node", "id": 152312684, "lat": -33.71076, "lon": 151.2928834}, {"type": "node", "id": 152315025, "lat": -33.7086785, "lon": 151.2962265}, {"type": "node", "id": 152391835, "lat": -33.7061631, "lon": 151.2971139}, {"type": "node", "id": 152406392, "lat": -33.7078475, "lon": 151.2966343, "tags": {"highway": "traffic_signals"}}, {"type": "node", "id": 152414495, "lat": -33.7066007, "lon": 151.2970088}, {"type": "node", "id": 158929634, "lat": -33.7088167, "lon": 151.2962975, "tags": {"note": "split placed here as the road has little witch hats that prevent lane change past this point"}}, {"type": "node", "id": 158929636, "lat": -33.7092869, "lon": 151.2961834}, {"type": "node", "id": 158929637, "lat": -33.7098737, "lon": 151.296157}, {"type": "node", "id": 158929638, "lat": -33.7100946, "lon": 151.2961684}, {"type": "node", "id": 158929639, "lat": -33.7104849, "lon": 151.2962499}, {"type": "node", "id": 158933467, "lat": -33.7101079, "lon": 151.295848, "tags": {"highway": "traffic_signals", "traffic_signals:direction": "forward"}}, {"type": "node", "id": 158934437, "lat": -33.7103573, "lon": 151.294247}, {"type": "node", "id": 158934546, "lat": -33.7103612, "lon": 151.2948127}, {"type": "node", "id": 246014276, "lat": -33.7026161, "lon": 151.2979566}, {"type": "node", "id": 1821307265, "lat": -33.7110041, "lon": 151.2963709}, {"type": "node", "id": 1821307273, "lat": -33.7109182, "lon": 151.2964127}, {"type": "node", "id": 1821307277, "lat": -33.7119101, "lon": 151.296933}, {"type": "node", "id": 1833197374, "lat": -33.7122336, "lon": 151.2971138}, {"type": "node", "id": 1833197377, "lat": -33.7112129, "lon": 151.2965367}, {"type": "node", "id": 1833197400, "lat": -33.7124322, "lon": 151.2971754}, {"type": "node", "id": 1833221594, "lat": -33.7095733, "lon": 151.2959047}, {"type": "node", "id": 1833221600, "lat": -33.7106667, "lon": 151.296289}, {"type": "node", "id": 1833221602, "lat": -33.7100362, "lon": 151.2959334, "tags": {"crossing": "traffic_signals", "highway": "crossing"}}, {"type": "node", "id": 1833221638, "lat": -33.7104894, "lon": 151.2961754}, {"type": "node", "id": 1833232141, "lat": -33.7077765, "lon": 151.296662, "tags": {"button_operated": "yes", "crossing": "traffic_signals", "highway": "crossing", "kerb": "lowered", "tactile_paving": "no", "traffic_signals:sound": "yes", "traffic_signals:vibration": "yes"}}, {"type": "node", "id": 1833232142, "lat": -33.7055633, "lon": 151.297331}, {"type": "node", "id": 1833232144, "lat": -33.706157, "lon": 151.2972159}, {"type": "node", "id": 1833232145, "lat": -33.7067412, "lon": 151.2970659}, {"type": "node", "id": 1833232147, "lat": -33.7106492, "lon": 151.2937333}, {"type": "node", "id": 1833250808, "lat": -33.7033501, "lon": 151.2976963}, {"type": "node", "id": 1833250809, "lat": -33.7031369, "lon": 151.2977779}, {"type": "node", "id": 1833250810, "lat": -33.7024877, "lon": 151.2981634}, {"type": "node", "id": 1833250811, "lat": -33.7049483, "lon": 151.2973303}, {"type": "node", "id": 1833250813, "lat": -33.7031588, "lon": 151.2976854}, {"type": "node", "id": 1833250815, "lat": -33.7033677, "lon": 151.2976158}, {"type": "node", "id": 1833250818, "lat": -33.7059468, "lon": 151.2972568}, {"type": "node", "id": 1833250837, "lat": -33.7041602, "lon": 151.2975649}, {"type": "node", "id": 1833250839, "lat": -33.7056161, "lon": 151.2972141}, {"type": "node", "id": 1833250841, "lat": -33.7063736, "lon": 151.2971726}, {"type": "node", "id": 1833250843, "lat": -33.7041543, "lon": 151.2974692}, {"type": "node", "id": 1833250844, "lat": -33.7063836, "lon": 151.2970703}, {"type": "node", "id": 1833737989, "lat": -33.7109734, "lon": 151.2922858}, {"type": "node", "id": 1833738000, "lat": -33.7110286, "lon": 151.2916024}, {"type": "node", "id": 2358087149, "lat": -33.7105488, "lon": 151.2941233}, {"type": "node", "id": 2358087150, "lat": -33.7108474, "lon": 151.2929601}, {"type": "node", "id": 3101733670, "lat": -33.709831, "lon": 151.2961532, "tags": {"crossing": "traffic_signals", "highway": "traffic_signals", "traffic_signals": "signal", "traffic_signals:direction": "forward", "traffic_signals:sound": "yes"}}, {"type": "node", "id": 3939180960, "lat": -33.7065875, "lon": 151.2971151}, {"type": "node", "id": 3963632501, "lat": -33.7109969, "lon": 151.2921309}, {"type": "node", "id": 6208259392, "lat": -33.7074043, "lon": 151.296702}, {"type": "node", "id": 6208259394, "lat": -33.7076849, "lon": 151.2965921}, {"type": "node", "id": 6229439110, "lat": -33.7109713, "lon": 151.2909644}, {"type": "node", "id": 6229439111, "lat": -33.7110027, "lon": 151.2912042}, {"type": "node", "id": 6265782450, "lat": -33.7101229, "lon": 151.2954857}, {"type": "node", "id": 6265782451, "lat": -33.7102748, "lon": 151.2951208}, {"type": "node", "id": 6265782455, "lat": -33.7069596, "lon": 151.2969833}, {"type": "node", "id": 6265782464, "lat": -33.7100236, "lon": 151.2956519, "tags": {"button_operated": "yes", "crossing": "traffic_signals", "highway": "crossing", "kerb": "flush", "tactile_paving": "no", "traffic_signals:sound": "yes", "traffic_signals:vibration": "yes"}}, {"type": "node", "id": 6265782476, "lat": -33.7108805, "lon": 151.2928279}, {"type": "node", "id": 6265782481, "lat": -33.7099785, "lon": 151.2958782}, {"type": "node", "id": 6265782482, "lat": -33.7099975, "lon": 151.2957991}, {"type": "node", "id": 6265782885, "lat": -33.7114953, "lon": 151.2966936}, {"type": "node", "id": 6265782886, "lat": -33.710282, "lon": 151.2962001}, {"type": "node", "id": 6265782887, "lat": -33.709707, "lon": 151.2961496}, {"type": "node", "id": 6265782890, "lat": -33.7095033, "lon": 151.2961545}, {"type": "node", "id": 6265782891, "lat": -33.7093973, "lon": 151.2961659}, {"type": "node", "id": 6265782892, "lat": -33.7091809, "lon": 151.2962041}, {"type": "node", "id": 6265782894, "lat": -33.7089672, "lon": 151.2962551}, {"type": "node", "id": 6267934854, "lat": -33.7022225, "lon": 151.2982486}, {"type": "node", "id": 6267934855, "lat": -33.7028049, "lon": 151.2979469}, {"type": "node", "id": 6267934856, "lat": -33.7029544, "lon": 151.2977658}, {"type": "node", "id": 7035725421, "lat": -33.7109092, "lon": 151.2906295}, {"type": "node", "id": 7166036982, "lat": -33.7107839, "lon": 151.2901689}, {"type": "node", "id": 7166036983, "lat": -33.711022, "lon": 151.2913977}, {"type": "node", "id": 7166036984, "lat": -33.7110133, "lon": 151.2919722}, {"type": "node", "id": 7213875965, "lat": -33.7077531, "lon": 151.2965659, "tags": {"button_operated": "yes", "crossing": "traffic_signals", "highway": "crossing", "kerb": "lowered", "tactile_paving": "no", "traffic_signals:sound": "yes", "traffic_signals:vibration": "yes"}}, {"type": "node", "id": 7213875966, "lat": -33.7079517, "lon": 151.296595, "tags": {"button_operated": "yes", "crossing": "traffic_signals", "highway": "crossing", "kerb": "lowered", "tactile_paving": "no", "traffic_signals:sound": "yes", "traffic_signals:vibration": "yes"}}, {"type": "node", "id": 7213875967, "lat": -33.7079322, "lon": 151.2964991, "tags": {"button_operated": "yes", "crossing": "traffic_signals", "highway": "crossing", "kerb": "lowered", "traffic_signals:sound": "yes"}}, {"type": "node", "id": 7302194067, "lat": -33.7106773, "lon": 151.2931708}, {"type": "node", "id": 8639135987, "lat": -33.7025615, "lon": 151.2979971}, {"type": "node", "id": 11294426244, "lat": -33.7109883, "lon": 151.2910887}, {"type": "node", "id": 11294426245, "lat": -33.7109431, "lon": 151.290801}, {"type": "node", "id": 11294426264, "lat": -33.7109181, "lon": 151.2926254}, {"type": "node", "id": 11294518070, "lat": -33.7100793, "lon": 151.2958338, "tags": {"crossing": "traffic_signals", "highway": "crossing"}}, {"type": "node", "id": 11294518073, "lat": -33.7101684, "lon": 151.2953974}, {"type": "node", "id": 11294564099, "lat": -33.7097853, "lon": 151.2958254, "tags": {"crossing": "traffic_signals", "highway": "crossing"}}, {"type": "node", "id": 11294564100, "lat": -33.7099304, "lon": 151.296159, "tags": {"crossing": "traffic_signals", "highway": "crossing"}}, {"type": "way", "id": 4334872, "nodes": [26381274, 1833737989, 3963632501, 7166036984, 26381272, 1833738000, 7166036983, 6229439111, 11294426244, 6229439110, 11294426245, 7035725421, 26381271, 7166036982, 152289351], "tags": {"bicycle": "yes", "cycleway": "no", "destination:forward": "Oxford Falls;Frenchs Forest;Chatswood;Sydney", "highway": "primary", "lanes": "2", "lanes:backward": "1", "lanes:forward": "1", "maxspeed": "70", "name": "Wakehurst Parkway", "overtaking": "no", "shoulder": "yes", "surface": "asphalt"}}, {"type": "way", "id": 4334877, "nodes": [6265782464, 6265782450, 11294518073, 26381638, 6265782451, 158934546, 21401208], "tags": {"cycleway:left": "no", "highway": "primary", "lanes": "2", "maxspeed": "70", "name": "Wakehurst Parkway", "oneway": "yes", "surface": "asphalt"}}, {"type": "way", "id": 15379360, "nodes": [152312684, 7302194067, 21401209, 152301256], "tags": {"highway": "primary", "lanes": "2", "maxspeed": "70", "name": "Wakehurst Parkway", "oneway": "yes", "surface": "asphalt"}}, {"type": "way", "id": 22371010, "nodes": [60570651, 29699074], "tags": {"bridge": "yes", "highway": "trunk", "lanes": "3", "lanes:bus:conditional": "1 @ (Mo-Fr 06:00-10:00)", "layer": "1", "maxspeed": "70", "maxspeed:conditional": "40 @ (Mo-Fr 08:00-09:30,14:30-16:00; PH off; SH off)", "name": "Pittwater Road", "network": "AU:NSW", "old_network": "MR", "old_ref": "10", "oneway": "yes", "placement": "right_of:2", "ref": "A8", "ref:start_date": "2013-05-23", "surface": "paved"}}, {"type": "way", "id": 22371012, "nodes": [152302463, 60570416], "tags": {"bridge": "yes", "highway": "trunk", "lanes": "3", "lanes:bus": "1", "lanes:bus:conditional": "1 @ (Mo-Fr 15:00-19:00)", "layer": "1", "maxspeed": "70", "maxspeed:conditional": "40 @ (Mo-Fr 08:00-09:30,14:30-16:00; PH off; SH off)", "name": "Pittwater Road", "network": "AU:NSW", "old_network": "MR", "old_ref": "10", "oneway": "yes", "ref": "A8", "surface": "paved"}}, {"type": "way", "id": 171031933, "nodes": [1821307277, 6265782885], "tags": {"bridge": "yes", "highway": "trunk", "lanes": "4", "layer": "1", "maxspeed": "60", "name": "Pittwater Road", "network": "AU:NSW", "old_network": "MR", "old_ref": "10", "ref": "A8", "ref:start_date": "2013-05-23", "surface": "paved"}}, {"type": "way", "id": 171031935, "nodes": [152311447, 7213875965, 6208259394, 6208259392, 152303284, 152414495, 1833250844, 152391835], "tags": {"highway": "trunk", "lanes": "3", "maxspeed": "70", "name": "Pittwater Road", "network": "AU:NSW", "old_network": "MR", "old_ref": "10", "oneway": "yes", "placement": "right_of:2", "ref": "A8", "surface": "paved"}}, {"type": "way", "id": 172414093, "nodes": [1833197400, 1833197374, 1821307277], "tags": {"highway": "trunk", "lanes": "4", "maxspeed": "60", "name": "Pittwater Road", "network": "AU:NSW", "old_network": "MR", "old_ref": "10", "ref": "A8", "ref:start_date": "2013-05-23", "source": "knowledge", "surface": "paved"}}, {"type": "way", "id": 172417931, "nodes": [21401211, 6265782481, 1833221602, 1833221638, 1833221600], "tags": {"foot": "no", "highway": "trunk", "lanes": "2", "lit": "yes", "maxspeed": "70", "name": "Pittwater Road", "network": "AU:NSW", "old_network": "MR", "old_ref": "10", "oneway": "yes", "ref": "A8", "ref:start_date": "2013-05-23", "shoulder": "no", "sidewalk": "no", "surface": "asphalt"}}, {"type": "way", "id": 172418492, "nodes": [2358087149, 1833232147, 2358087150], "tags": {"cycleway:left": "no", "highway": "primary", "lanes": "2", "maxspeed": "70", "name": "Wakehurst Parkway", "oneway": "yes", "surface": "asphalt"}}, {"type": "way", "id": 172420789, "nodes": [29699074, 1833250837], "tags": {"highway": "trunk", "lanes": "3", "lanes:bus:conditional": "1 @ (Mo-Fr 06:00-10:00)", "maxspeed": "70", "maxspeed:conditional": "40 @ (Mo-Fr 08:00-09:30,14:30-16:00; PH off; SH off)", "name": "Pittwater Road", "network": "AU:NSW", "old_network": "MR", "old_ref": "10", "oneway": "yes", "placement": "right_of:2", "ref": "A8", "ref:start_date": "2013-05-23", "surface": "paved"}}, {"type": "way", "id": 172420790, "nodes": [1833232142, 1833250818, 1833232144, 1833250841, 3939180960, 1833232145, 6265782455], "tags": {"highway": "trunk", "lanes": "3", "lanes:bus": "1", "lanes:bus:conditional": "1 @ (Mo-Fr 06:00-10:00)", "maxspeed": "70", "name": "Pittwater Road", "network": "AU:NSW", "old_network": "MR", "old_ref": "10", "oneway": "yes", "placement": "right_of:2", "ref": "A8", "ref:start_date": "2013-05-23", "shoulder": "no", "surface": "paved"}}, {"type": "way", "id": 172420791, "nodes": [1833250811, 1833250843, 152302463], "tags": {"highway": "trunk", "lanes": "3", "lanes:bus": "1", "lanes:bus:conditional": "1 @ (Mo-Fr 15:00-19:00)", "maxspeed": "70", "maxspeed:conditional": "40 @ (Mo-Fr 08:00-09:30,14:30-16:00; PH off; SH off)", "name": "Pittwater Road", "network": "AU:NSW", "old_network": "MR", "old_ref": "10", "oneway": "yes", "ref": "A8", "surface": "paved"}}, {"type": "way", "id": 172422252, "nodes": [60570649, 1833250810, 6267934855, 60570650, 1833250809, 1833250808, 60570651], "tags": {"highway": "trunk", "lanes": "3", "lanes:bus": "1", "lanes:bus:conditional": "1 @ (Mo-Fr 06:00-10:00)", "maxspeed": "70", "maxspeed:conditional": "40 @ (Mo-Fr 08:00-09:30,14:30-16:00; PH off; SH off)", "name": "Pittwater Road", "network": "AU:NSW", "old_network": "MR", "old_ref": "10", "oneway": "yes", "placement": "right_of:2", "ref": "A8", "ref:start_date": "2013-05-23", "surface": "paved"}}, {"type": "way", "id": 223237228, "nodes": [1833221600, 1821307273], "tags": {"highway": "trunk", "lanes": "4", "lanes:bus": "1", "maxspeed": "70", "name": "Pittwater Road", "network": "AU:NSW", "old_network": "MR", "old_ref": "10", "oneway": "yes", "placement": "transition", "ref": "A8", "ref:start_date": "2013-05-23", "surface": "paved", "turn:lanes": "merge_to_right|||"}}, {"type": "way", "id": 569396706, "nodes": [158929634, 6265782894, 6265782892, 158929636, 6265782891, 6265782890, 6265782887, 3101733670, 158929637, 11294564100, 158929638, 6265782886, 158929639, 1833221600], "tags": {"highway": "trunk", "lanes": "3", "lanes:bus": "1", "lanes:bus:conditional": "1 @ (Mo-Fr 06:00-10:00)", "maxspeed": "70", "name": "Pittwater Road", "network": "AU:NSW", "old_network": "MR", "old_ref": "10", "oneway": "yes", "ref": "A8", "ref:start_date": "2013-05-23", "shoulder": "no", "surface": "paved"}}, {"type": "way", "id": 569398890, "nodes": [1833197377, 1821307265], "tags": {"highway": "trunk", "lanes": "3", "lanes:bus": "1", "lit": "yes", "maxspeed": "70", "name": "Pittwater Road", "network": "AU:NSW", "old_network": "MR", "old_ref": "10", "oneway": "yes", "placement": "right_of:2", "ref": "A8", "source:maxspeed": "local_knowledge", "surface": "paved"}}, {"type": "way", "id": 569716099, "nodes": [2358087150, 6265782476, 11294426264, 26381274], "tags": {"highway": "primary", "lanes": "2", "maxspeed": "70", "name": "Wakehurst Parkway", "oneway": "yes", "surface": "asphalt"}}, {"type": "way", "id": 569716100, "nodes": [26381274, 152312684], "tags": {"highway": "primary", "lanes": "1", "lit": "yes", "maxspeed": "70", "name": "Wakehurst Parkway", "oneway": "yes", "surface": "asphalt"}}, {"type": "way", "id": 576429047, "nodes": [152298685, 1833250811], "tags": {"highway": "trunk", "lanes": "3", "lanes:bus": "1", "maxspeed": "70", "name": "Pittwater Road", "network": "AU:NSW", "old_network": "MR", "old_ref": "10", "oneway": "yes", "ref": "A8", "surface": "paved"}}, {"type": "way", "id": 576429049, "nodes": [1833250837, 29612711], "tags": {"highway": "trunk", "lanes": "4", "lanes:bus": "1", "lanes:bus:conditional": "1 @ (Mo-Fr 06:00-10:00)", "maxspeed": "70", "name": "Pittwater Road", "network": "AU:NSW", "old_network": "MR", "old_ref": "10", "oneway": "yes", "placement": "right_of:2", "ref": "A8", "ref:start_date": "2013-05-23", "surface": "paved", "turn:lanes": "|||right"}}, {"type": "way", "id": 576429148, "nodes": [29612711, 1833232142], "tags": {"highway": "trunk", "lanes": "4", "lanes:bus": "1", "lanes:bus:conditional": "1 @ (Mo-Fr 06:00-10:00)", "lit": "yes", "maxspeed": "70", "name": "Pittwater Road", "network": "AU:NSW", "old_network": "MR", "old_ref": "10", "oneway": "yes", "placement": "right_of:2", "ref": "A8", "ref:start_date": "2013-05-23", "shoulder": "no", "surface": "asphalt", "turn:lanes": "|||merge_to_left"}}, {"type": "way", "id": 576429149, "nodes": [1833250839, 152298685], "tags": {"highway": "trunk", "lanes": "4", "lanes:bus": "1", "maxspeed": "70", "name": "Pittwater Road", "network": "AU:NSW", "old_network": "MR", "old_ref": "10", "oneway": "yes", "ref": "A8", "shoulder": "no", "surface": "paved", "turn:lanes": "left|||"}}, {"type": "way", "id": 576429244, "nodes": [21401208, 2358087149], "tags": {"cycleway:left": "no", "highway": "primary", "lanes": "2", "maxspeed": "70", "name": "Wakehurst Parkway", "oneway": "yes", "surface": "asphalt"}}, {"type": "way", "id": 576429247, "nodes": [152301256, 158934437], "tags": {"highway": "primary", "maxspeed": "70", "name": "Wakehurst Parkway", "oneway": "yes", "surface": "asphalt"}}, {"type": "way", "id": 576429632, "nodes": [152307818, 158929634], "tags": {"highway": "trunk", "lanes": "4", "lanes:bus": "1", "lanes:bus:conditional": "1 @ (Mo-Fr 06:00-10:00)", "lit": "yes", "maxspeed": "70", "name": "Pittwater Road", "network": "AU:NSW", "old_network": "MR", "old_ref": "10", "oneway": "yes", "placement": "transition", "ref": "A8", "ref:start_date": "2013-05-23", "shoulder": "no", "surface": "asphalt", "turn:lanes": "|||right"}}, {"type": "way", "id": 576429633, "nodes": [26381650, 152315025], "tags": {"highway": "trunk", "lanes": "3", "maxspeed": "70", "name": "Pittwater Road", "network": "AU:NSW", "old_network": "MR", "old_ref": "10", "oneway": "yes", "ref": "A8", "shoulder": "no", "surface": "paved"}}, {"type": "way", "id": 576429634, "nodes": [21401211, 11294564099, 1833221594, 26381649], "tags": {"highway": "trunk", "lanes": "3", "lanes:bus": "1", "maxspeed": "70", "name": "Pittwater Road", "network": "AU:NSW", "old_network": "MR", "old_ref": "10", "oneway": "yes", "placement": "right_of:2", "ref": "A8", "shoulder": "no", "surface": "paved"}}, {"type": "way", "id": 576429795, "nodes": [152406392, 7213875966, 152307818], "tags": {"highway": "trunk", "lanes": "3", "lanes:bus": "1", "lanes:bus:conditional": "1 @ (Mo-Fr 06:00-10:00)", "lit": "yes", "maxspeed": "70", "name": "Pittwater Road", "network": "AU:NSW", "old_network": "MR", "old_ref": "10", "oneway": "yes", "placement": "right_of:2", "ref": "A8", "ref:start_date": "2013-05-23", "surface": "concrete"}}, {"type": "way", "id": 576429796, "nodes": [152315025, 7213875967, 152311447], "tags": {"highway": "trunk", "lanes": "3", "maxspeed": "70", "name": "Pittwater Road", "network": "AU:NSW", "old_network": "MR", "old_ref": "10", "oneway": "yes", "placement": "right_of:2", "ref": "A8", "surface": "paved"}}, {"type": "way", "id": 576430372, "nodes": [11294518070, 6265782482, 21401211], "tags": {"highway": "trunk", "lanes": "3", "lanes:bus": "1", "lit": "yes", "maxspeed": "60", "name": "Pittwater Road", "network": "AU:NSW", "old_network": "MR", "old_ref": "10", "oneway": "yes", "placement": "right_of:2", "ref": "A8", "shoulder": "no", "source:maxspeed": "local_knowledge", "surface": "asphalt"}}, {"type": "way", "id": 669115978, "nodes": [152391835, 1833250839], "tags": {"highway": "trunk", "lanes": "3", "maxspeed": "70", "name": "Pittwater Road", "network": "AU:NSW", "old_network": "MR", "old_ref": "10", "oneway": "yes", "placement": "right_of:1", "ref": "A8", "shoulder": "no", "surface": "paved", "turn:lanes": "left||"}}, {"type": "way", "id": 669115979, "nodes": [21401211, 6265782464], "tags": {"cycleway:left": "no", "highway": "primary", "lanes": "2", "maxspeed": "70", "name": "Wakehurst Parkway", "oneway": "yes", "placement": "transition", "shoulder": "no", "surface": "asphalt"}}, {"type": "way", "id": 669115981, "nodes": [6265782455, 152296038, 1833232141, 152406392], "tags": {"highway": "trunk", "lanes": "4", "lanes:bus": "1", "lanes:bus:conditional": "1 @ (Mo-Fr 06:00-10:00)", "maxspeed": "70", "name": "Pittwater Road", "network": "AU:NSW", "old_network": "MR", "old_ref": "10", "oneway": "yes", "placement": "right_of:2", "ref": "A8", "ref:start_date": "2013-05-23", "surface": "paved", "turn:lanes": "|||right"}}, {"type": "way", "id": 669115984, "nodes": [26381649, 26381650], "tags": {"highway": "trunk", "lanes": "4", "lit": "yes", "maxspeed": "70", "name": "Pittwater Road", "network": "AU:NSW", "old_network": "MR", "old_ref": "10", "oneway": "yes", "placement": "right_of:2", "ref": "A8", "shoulder": "no", "sidewalk": "left", "surface": "asphalt"}}, {"type": "way", "id": 669115994, "nodes": [1821307273, 1833197377], "tags": {"highway": "trunk", "lanes": "2", "lit": "yes", "maxspeed": "60", "name": "Pittwater Road", "network": "AU:NSW", "old_network": "MR", "old_ref": "10", "oneway": "yes", "placement": "transition", "ref": "A8", "ref:start_date": "2013-05-23", "sidewalk": "no", "surface": "asphalt"}}, {"type": "way", "id": 669115996, "nodes": [6265782885, 1833197377], "tags": {"highway": "trunk", "lanes": "4", "layer": "1", "lit": "yes", "maxspeed": "60", "name": "Pittwater Road", "network": "AU:NSW", "old_network": "MR", "old_ref": "10", "ref": "A8", "ref:start_date": "2013-05-23", "surface": "asphalt"}}, {"type": "way", "id": 669343600, "nodes": [60570416, 1833250815, 1833250813, 6267934856, 60570377, 246014276, 8639135987, 6267934854], "tags": {"highway": "trunk", "lanes": "3", "lanes:bus": "1", "lanes:bus:conditional": "1 @ (Mo-Fr 15:00-19:00)", "maxspeed": "70", "maxspeed:conditional": "40 @ (Mo-Fr 08:00-09:30,14:30-16:00; PH off; SH off)", "name": "Pittwater Road", "network": "AU:NSW", "old_network": "MR", "old_ref": "10", "oneway": "yes", "placement": "right_of:2", "ref": "A8", "surface": "paved"}}, {"type": "way", "id": 732695943, "nodes": [1821307265, 158933467, 11294518070], "tags": {"highway": "trunk", "lanes": "3", "lanes:bus": "1", "lit": "yes", "maxspeed": "70", "name": "Pittwater Road", "network": "AU:NSW", "old_network": "MR", "old_ref": "10", "oneway": "yes", "placement": "right_of:2", "ref": "A8", "shoulder": "no", "source:maxspeed": "local_knowledge", "surface": "paved"}}]}