{"version": 0.6, "generator": "Overpass API 0.7.61.5 4133829e", "osm3s": {"timestamp_osm_base": "2023-12-06T09:19:29Z", "copyright": "The data included in this document is from www.openstreetmap.org. The data is made available under ODbL."}, "elements": [{"type": "node", "id": 60106787, "lat": -33.9444006, "lon": 151.0346439}, {"type": "node", "id": 60106941, "lat": -33.9436927, "lon": 151.0349213}, {"type": "node", "id": 60106942, "lat": -33.9443902, "lon": 151.0347954}, {"type": "node", "id": 60108189, "lat": -33.9513466, "lon": 151.0383443}, {"type": "node", "id": 60108190, "lat": -33.9505446, "lon": 151.0383414}, {"type": "node", "id": 60108191, "lat": -33.9502227, "lon": 151.0382741}, {"type": "node", "id": 60108192, "lat": -33.949602, "lon": 151.0380212}, {"type": "node", "id": 60108193, "lat": -33.9490078, "lon": 151.0376213}, {"type": "node", "id": 60108195, "lat": -33.9468351, "lon": 151.0361518}, {"type": "node", "id": 60108196, "lat": -33.9457991, "lon": 151.0351431}, {"type": "node", "id": 60108197, "lat": -33.9452213, "lon": 151.0347603, "tags": {"highway": "traffic_signals", "traffic_signals": "traffic_lights", "traffic_signals:direction": "forward"}}, {"type": "node", "id": 60108591, "lat": -33.9448351, "lon": 151.0348082, "tags": {"highway": "traffic_signals", "traffic_signals": "traffic_lights", "traffic_signals:direction": "forward"}}, {"type": "node", "id": 60108599, "lat": -33.9500879, "lon": 151.0383703}, {"type": "node", "id": 60108601, "lat": -33.9512074, "lon": 151.0384715}, {"type": "node", "id": 60108602, "lat": -33.9526198, "lon": 151.0383366}, {"type": "node", "id": 60108603, "lat": -33.9539054, "lon": 151.0382133, "tags": {"highway": "traffic_signals"}}, {"type": "node", "id": 252781130, "lat": -33.945566, "lon": 151.0351364}, {"type": "node", "id": 262870821, "lat": -33.9467237, "lon": 151.0360577}, {"type": "node", "id": 262872838, "lat": -33.9507854, "lon": 151.0383649}, {"type": "node", "id": 262872976, "lat": -33.9518635, "lon": 151.0382955}, {"type": "node", "id": 262872977, "lat": -33.9516808, "lon": 151.0383135}, {"type": "node", "id": 262872978, "lat": -33.9516784, "lon": 151.0384275}, {"type": "node", "id": 262872983, "lat": -33.9518683, "lon": 151.0384085}, {"type": "node", "id": 262873843, "lat": -33.9480808, "lon": 151.0370024}, {"type": "node", "id": 1181956852, "lat": -33.949963, "lon": 151.0381869}, {"type": "node", "id": 1181956855, "lat": -33.9493554, "lon": 151.0378743}, {"type": "node", "id": 1181956883, "lat": -33.9498298, "lon": 151.0381319}, {"type": "node", "id": 1186815865, "lat": -33.9446199, "lon": 151.0347879}, {"type": "node", "id": 1197904306, "lat": -33.9510118, "lon": 151.0383695}, {"type": "node", "id": 1672761393, "lat": -33.9519948, "lon": 151.0382829}, {"type": "node", "id": 1672761395, "lat": -33.9525054, "lon": 151.038234}, {"type": "node", "id": 1672789179, "lat": -33.9452023, "lon": 151.0349175}, {"type": "node", "id": 1672789183, "lat": -33.9457912, "lon": 151.0353246}, {"type": "node", "id": 1672789185, "lat": -33.9459627, "lon": 151.0354883}, {"type": "node", "id": 1672789187, "lat": -33.9467316, "lon": 151.0362106}, {"type": "node", "id": 1672789192, "lat": -33.9469042, "lon": 151.0363442}, {"type": "node", "id": 1672789193, "lat": -33.9473656, "lon": 151.0366723}, {"type": "node", "id": 1672789194, "lat": -33.9480167, "lon": 151.0371354}, {"type": "node", "id": 1672789197, "lat": -33.9483053, "lon": 151.0373271}, {"type": "node", "id": 1672789201, "lat": -33.9487701, "lon": 151.0376389}, {"type": "node", "id": 1672789203, "lat": -33.9492738, "lon": 151.0379771}, {"type": "node", "id": 1672789205, "lat": -33.9496949, "lon": 151.0382161}, {"type": "node", "id": 1672789207, "lat": -33.95025, "lon": 151.0384162}, {"type": "node", "id": 1672789210, "lat": -33.9507497, "lon": 151.038484}, {"type": "node", "id": 1837096569, "lat": -33.9446973, "lon": 151.0346346}, {"type": "node", "id": 1837096571, "lat": -33.9448258, "lon": 151.0346489}, {"type": "node", "id": 1837096572, "lat": -33.9455078, "lon": 151.0349099}, {"type": "node", "id": 1837098952, "lat": -33.944052, "lon": 151.0348486}, {"type": "node", "id": 1837098954, "lat": -33.9453512, "lon": 151.0349934}, {"type": "node", "id": 1837098955, "lat": -33.9454916, "lon": 151.0350834}, {"type": "node", "id": 1837106954, "lat": -33.9457124, "lon": 151.0350621}, {"type": "node", "id": 1838376309, "lat": -33.9472969, "lon": 151.0364794}, {"type": "node", "id": 1838376314, "lat": -33.943241, "lon": 151.0350136}, {"type": "node", "id": 1838376315, "lat": -33.9440517, "lon": 151.0347085}, {"type": "node", "id": 1838376316, "lat": -33.9464095, "lon": 151.0357639}, {"type": "node", "id": 1838377594, "lat": -33.952527, "lon": 151.0383467}, {"type": "node", "id": 1838377596, "lat": -33.9528959, "lon": 151.0383102}, {"type": "node", "id": 1838377611, "lat": -33.9532275, "lon": 151.0382783}, {"type": "node", "id": 1861495628, "lat": -33.9511772, "lon": 151.0383587}, {"type": "node", "id": 3074485497, "lat": -33.9466153, "lon": 151.0361113}, {"type": "node", "id": 4019502730, "lat": -33.9435498, "lon": 151.0348122}, {"type": "node", "id": 4019502740, "lat": -33.9445112, "lon": 151.0347884}, {"type": "node", "id": 4019502741, "lat": -33.9449361, "lon": 151.0346701}, {"type": "node", "id": 4019502743, "lat": -33.9442701, "lon": 151.0346631}, {"type": "node", "id": 4019502755, "lat": -33.9442614, "lon": 151.0348114}, {"type": "node", "id": 4019502757, "lat": -33.945091, "lon": 151.0348733}, {"type": "node", "id": 4019502767, "lat": -33.9428608, "lon": 151.0350938, "tags": {"crossing": "traffic_signals", "highway": "crossing"}}, {"type": "node", "id": 4910357432, "lat": -33.9527528, "lon": 151.0382112}, {"type": "node", "id": 5640733764, "lat": -33.953897, "lon": 151.0381028, "tags": {"highway": "traffic_signals"}}, {"type": "node", "id": 5640733766, "lat": -33.9537819, "lon": 151.038225, "tags": {"crossing": "traffic_signals"}}, {"type": "node", "id": 5640733767, "lat": -33.9537783, "lon": 151.0381139, "tags": {"crossing": "traffic_signals"}}, {"type": "node", "id": 5640733775, "lat": -33.948482, "lon": 151.0374467}, {"type": "node", "id": 5640733776, "lat": -33.9495885, "lon": 151.0381635}, {"type": "node", "id": 5640733777, "lat": -33.9498271, "lon": 151.0382768}, {"type": "node", "id": 5640733778, "lat": -33.9501135, "lon": 151.0382413}, {"type": "node", "id": 5714726430, "lat": -33.9484253, "lon": 151.0372328}, {"type": "node", "id": 5714726431, "lat": -33.9488038, "lon": 151.0374862}, {"type": "node", "id": 5714726434, "lat": -33.9491724, "lon": 151.0377464}, {"type": "node", "id": 5714726435, "lat": -33.9494277, "lon": 151.038073}, {"type": "node", "id": 5714726436, "lat": -33.9494655, "lon": 151.0379429}, {"type": "node", "id": 5714726437, "lat": -33.9497114, "lon": 151.0380757}, {"type": "node", "id": 5714726438, "lat": -33.9499294, "lon": 151.0383157}, {"type": "node", "id": 5714726439, "lat": -33.9503811, "lon": 151.038311}, {"type": "node", "id": 5714726440, "lat": -33.9504016, "lon": 151.0384465}, {"type": "node", "id": 5714726441, "lat": -33.9505368, "lon": 151.0384666}, {"type": "node", "id": 5714726442, "lat": -33.9506369, "lon": 151.0384753}, {"type": "node", "id": 5714726443, "lat": -33.9506725, "lon": 151.0383573}, {"type": "node", "id": 5714726444, "lat": -33.9508973, "lon": 151.0383701}, {"type": "node", "id": 5714726445, "lat": -33.9508578, "lon": 151.0384861}, {"type": "node", "id": 5714726446, "lat": -33.9509673, "lon": 151.0384861}, {"type": "node", "id": 5714726447, "lat": -33.9510797, "lon": 151.0384807}, {"type": "node", "id": 5714726448, "lat": -33.9512403, "lon": 151.0383543}, {"type": "node", "id": 5714726454, "lat": -33.9522723, "lon": 151.0383699}, {"type": "node", "id": 5714726455, "lat": -33.9532228, "lon": 151.038167}, {"type": "node", "id": 5727386623, "lat": -33.9448684, "lon": 151.0348152, "tags": {"button_operated": "yes", "crossing": "traffic_signals", "crossing:markings": "dashes", "highway": "crossing"}}, {"type": "node", "id": 5727386624, "lat": -33.9449683, "lon": 151.0346787, "tags": {"button_operated": "yes", "crossing": "traffic_signals", "crossing:markings": "dashes", "highway": "crossing"}}, {"type": "node", "id": 5727386634, "lat": -33.9445498, "lon": 151.0346297}, {"type": "node", "id": 5727386635, "lat": -33.9441526, "lon": 151.0348302}, {"type": "node", "id": 5727386638, "lat": -33.9447451, "lon": 151.0347953}, {"type": "node", "id": 5727386639, "lat": -33.9453637, "lon": 151.0348262}, {"type": "node", "id": 5727386640, "lat": -33.9456106, "lon": 151.0349804}, {"type": "node", "id": 5727386641, "lat": -33.9456805, "lon": 151.0352262}, {"type": "node", "id": 5727386642, "lat": -33.9459617, "lon": 151.0353082}, {"type": "node", "id": 5727386643, "lat": -33.9461285, "lon": 151.0356556}, {"type": "node", "id": 5727386644, "lat": -33.9461461, "lon": 151.0354958}, {"type": "node", "id": 5727386645, "lat": -33.9462921, "lon": 151.0358232}, {"type": "node", "id": 5727386646, "lat": -33.9464642, "lon": 151.0359823}, {"type": "node", "id": 5727386647, "lat": -33.9465742, "lon": 151.0359247}, {"type": "node", "id": 5727386648, "lat": -33.9469243, "lon": 151.0362207}, {"type": "node", "id": 5727386649, "lat": -33.9471066, "lon": 151.0363515}, {"type": "node", "id": 5727386650, "lat": -33.9471837, "lon": 151.0365435}, {"type": "node", "id": 5727386651, "lat": -33.9478328, "lon": 151.0370082}, {"type": "node", "id": 5727386652, "lat": -33.947547, "lon": 151.0368042}, {"type": "node", "id": 5727386653, "lat": -33.9475769, "lon": 151.0366659}, {"type": "node", "id": 5727773788, "lat": -33.9483997, "lon": 151.037391}, {"type": "node", "id": 9385550025, "lat": -33.9428144, "lon": 151.0349645, "tags": {"crossing": "traffic_signals", "highway": "crossing"}}, {"type": "node", "id": 9385550027, "lat": -33.9428388, "lon": 151.0349595, "tags": {"highway": "traffic_signals", "traffic_signals": "signal", "traffic_signals:direction": "forward"}}, {"type": "node", "id": 9385550038, "lat": -33.9436691, "lon": 151.0347876}, {"type": "node", "id": 9385550041, "lat": -33.9433305, "lon": 151.0348576}, {"type": "node", "id": 9417592536, "lat": -33.9438225, "lon": 151.034895}, {"type": "node", "id": 9417592538, "lat": -33.9440841, "lon": 151.0348427}, {"type": "node", "id": 9456695768, "lat": -33.9507878, "lon": 151.0384847}, {"type": "node", "id": 9456695775, "lat": -33.9509285, "lon": 151.0384861}, {"type": "node", "id": 9456695778, "lat": -33.950997, "lon": 151.0384847}, {"type": "node", "id": 10740674179, "lat": -33.9450768, "lon": 151.034708}, {"type": "node", "id": 10740674180, "lat": -33.9449816, "lon": 151.0348391}, {"type": "node", "id": 10740674184, "lat": -33.9427702, "lon": 151.0351124}, {"type": "way", "id": 8039321, "nodes": [60106787, 4019502743, 1838376315, 9385550038, 4019502730, 9385550041, 9385550027, 9385550025], "tags": {"highway": "trunk", "lanes": "3", "maxspeed": "70", "name": "Fairford Road", "network": "AU:NSW", "old_network": "MR", "old_ref": "6", "oneway": "yes", "ref": "A6", "source:name": "knowledge", "surface": "asphalt"}}, {"type": "way", "id": 24278326, "nodes": [262872978, 262872983], "tags": {"bridge": "yes", "highway": "trunk", "lanes": "2", "layer": "1", "maxspeed": "70", "name": "Davies Road", "network": "AU:NSW", "old_network": "MR", "old_ref": "6", "oneway": "yes", "ref": "A6", "surface": "asphalt"}}, {"type": "way", "id": 24278334, "nodes": [262872977, 60108189, 5714726448, 1861495628, 1197904306, 5714726444, 262872838, 5714726443, 60108190, 5714726439, 60108191, 5640733778, 1181956852, 1181956883, 5714726437, 60108192, 5714726436, 1181956855], "tags": {"highway": "trunk", "lanes": "2", "name": "Davies Road", "network": "AU:NSW", "old_network": "MR", "old_ref": "6", "oneway": "yes", "ref": "A6", "source:name": "knowledge", "surface": "asphalt"}}, {"type": "way", "id": 24278337, "nodes": [262872976, 262872977], "tags": {"bridge": "yes", "highway": "trunk", "lanes": "2", "layer": "1", "name": "Davies Road", "network": "AU:NSW", "old_network": "MR", "old_ref": "6", "oneway": "yes", "ref": "A6", "surface": "asphalt"}}, {"type": "way", "id": 154805871, "nodes": [1672789192, 5727386650, 1672789193, 5727386652, 5727386651, 1672789194], "tags": {"highway": "trunk", "lanes": "2", "maxspeed": "70", "name": "Davies Road", "network": "AU:NSW", "old_network": "MR", "old_ref": "6", "oneway": "yes", "ref": "A6", "source:name": "knowledge", "surface": "asphalt"}}, {"type": "way", "id": 173006852, "nodes": [262872983, 5714726454, 1838377594, 60108602, 1838377596], "tags": {"highway": "trunk", "lanes": "2", "maxspeed": "70", "name": "Davies Road", "network": "AU:NSW", "old_network": "MR", "old_ref": "6", "oneway": "yes", "ref": "A6", "surface": "asphalt"}}, {"type": "way", "id": 225786962, "nodes": [10740674180, 10740674179], "tags": {"highway": "trunk", "name": "Watson Road", "surface": "asphalt"}}, {"type": "way", "id": 255870482, "nodes": [5640733764, 5640733767, 5714726455, 4910357432, 1672761395, 1672761393, 262872976], "tags": {"highway": "trunk", "lanes": "2", "maxspeed": "80", "name": "Davies Road", "network": "AU:NSW", "old_network": "MR", "old_ref": "6", "oneway": "yes", "ref": "A6", "source:name": "knowledge", "surface": "asphalt"}}, {"type": "way", "id": 264403847, "nodes": [10740674179, 5727386624, 4019502741, 1837096571, 1837096569, 5727386634, 60106787], "tags": {"highway": "trunk", "lanes": "3", "maxspeed": "70", "name": "Fairford Road", "network": "AU:NSW", "old_network": "MR", "old_ref": "6", "oneway": "yes", "ref": "A6", "source:name": "knowledge", "surface": "asphalt"}}, {"type": "way", "id": 385523653, "nodes": [10740674180, 4019502757, 1672789179, 1837098954, 1837098955, 252781130, 5727386641, 1672789183, 1672789185, 5727386643, 5727386645, 5727386646, 3074485497, 1672789187, 1672789192], "tags": {"highway": "trunk", "lanes": "3", "name": "Davies Road", "network": "AU:NSW", "old_network": "MR", "old_ref": "6", "oneway": "yes", "ref": "A6", "source:name": "knowledge", "surface": "asphalt"}}, {"type": "way", "id": 385523654, "nodes": [1181956855, 5714726434, 60108193], "tags": {"highway": "trunk", "lanes": "3", "maxspeed": "70", "name": "Davies Road", "network": "AU:NSW", "old_network": "MR", "old_ref": "6", "oneway": "yes", "ref": "A6", "source:name": "knowledge", "surface": "asphalt"}}, {"type": "way", "id": 399207900, "nodes": [1186815865, 5727386638, 60108591, 5727386623, 10740674180], "tags": {"highway": "trunk", "lanes": "4", "layer": "1", "maxspeed": "70", "name": "Fairford Road", "network": "AU:NSW", "old_network": "MR", "old_ref": "6", "oneway": "yes", "ref": "A6", "source:name": "knowledge", "surface": "concrete", "turn:lanes": "none|none|none|right"}}, {"type": "way", "id": 499829483, "nodes": [1838377596, 1838377611, 5640733766, 60108603], "tags": {"highway": "trunk", "lanes": "3", "name": "Davies Road", "network": "AU:NSW", "old_network": "MR", "old_ref": "6", "oneway": "yes", "ref": "A6", "source:location": "lpi_imagery", "surface": "asphalt", "turn:lanes": "none|none|right"}}, {"type": "way", "id": 760260487, "nodes": [262870821, 5727386647, 1838376316, 5727386644, 5727386642, 60108196, 1837106954, 5727386640, 1837096572, 5727386639], "tags": {"highway": "trunk", "lanes": "3", "maxspeed": "70", "name": "Davies Road", "network": "AU:NSW", "old_network": "MR", "old_ref": "6", "oneway": "yes", "ref": "A6", "source:name": "knowledge", "surface": "asphalt"}}, {"type": "way", "id": 784006861, "nodes": [5727386639, 60108197, 10740674179], "tags": {"highway": "trunk", "lanes": "3", "maxspeed": "70", "name": "Davies Road", "network": "AU:NSW", "old_network": "MR", "old_ref": "6", "oneway": "yes", "ref": "A6", "source:name": "knowledge", "surface": "asphalt"}}, {"type": "way", "id": 784006862, "nodes": [4019502755, 60106942, 4019502740, 1186815865], "tags": {"highway": "trunk", "lanes": "4", "layer": "1", "maxspeed": "70", "name": "Fairford Road", "network": "AU:NSW", "old_network": "MR", "old_ref": "6", "oneway": "yes", "ref": "A6", "source:name": "knowledge", "surface": "concrete", "turn:lanes": "none|none|none|right"}}, {"type": "way", "id": 874918317, "nodes": [1672789194, 1672789197, 5727773788, 5640733775, 1672789201, 1672789203, 5714726435, 5640733776, 1672789205, 5640733777, 5714726438, 60108599, 1672789207, 5714726440, 5714726441, 5714726442, 1672789210, 9456695768, 5714726445, 9456695775, 5714726446, 9456695778, 5714726447, 60108601, 262872978], "tags": {"highway": "trunk", "lanes": "2", "maxspeed": "70", "name": "Davies Road", "network": "AU:NSW", "old_network": "MR", "old_ref": "6", "oneway": "yes", "ref": "A6", "source:name": "knowledge", "surface": "asphalt"}}, {"type": "way", "id": 874918318, "nodes": [262873843, 5727386653, 1838376309, 5727386649, 5727386648, 60108195, 262870821], "tags": {"highway": "trunk", "lanes": "3", "maxspeed": "70", "name": "Davies Road", "network": "AU:NSW", "old_network": "MR", "old_ref": "6", "oneway": "yes", "ref": "A6", "source:name": "knowledge", "surface": "asphalt"}}, {"type": "way", "id": 874918319, "nodes": [60108193, 5714726431, 5714726430, 262873843], "tags": {"highway": "trunk", "lanes": "3", "maxspeed": "70", "name": "Davies Road", "network": "AU:NSW", "old_network": "MR", "old_ref": "6", "oneway": "yes", "ref": "A6", "source:name": "knowledge", "surface": "asphalt"}}, {"type": "way", "id": 1018261773, "nodes": [10740674184, 4019502767, 1838376314, 60106941, 9417592536, 1837098952, 9417592538, 5727386635, 4019502755], "tags": {"highway": "trunk", "lanes": "4", "maxspeed": "70", "name": "Fairford Road", "network": "AU:NSW", "old_network": "MR", "old_ref": "6", "oneway": "yes", "ref": "A6", "source:name": "knowledge", "surface": "concrete", "turn:lanes": "none|none|none|right"}}]}