{"version": 0.6, "generator": "Overpass API 0.7.61.5 4133829e", "osm3s": {"timestamp_osm_base": "2023-12-06T13:24:01Z", "copyright": "The data included in this document is from www.openstreetmap.org. The data is made available under ODbL."}, "elements": [{"type": "node", "id": 31207849, "lat": -17.2057626, "lon": 145.905694}, {"type": "node", "id": 31207850, "lat": -17.2074464, "lon": 145.9070497}, {"type": "node", "id": 31207851, "lat": -17.2078344, "lon": 145.9073277}, {"type": "node", "id": 31207852, "lat": -17.2086323, "lon": 145.9077834}, {"type": "node", "id": 31207854, "lat": -17.2127552, "lon": 145.9094215}, {"type": "node", "id": 31207855, "lat": -17.2132633, "lon": 145.9096376}, {"type": "node", "id": 31207856, "lat": -17.2136769, "lon": 145.9098332}, {"type": "node", "id": 31207857, "lat": -17.2143453, "lon": 145.9101896}, {"type": "node", "id": 31207858, "lat": -17.2147178, "lon": 145.9104111}, {"type": "node", "id": 31207859, "lat": -17.2150721, "lon": 145.9106339}, {"type": "node", "id": 31207860, "lat": -17.219658, "lon": 145.913776}, {"type": "node", "id": 31207861, "lat": -17.2218841, "lon": 145.9153726}, {"type": "node", "id": 31207862, "lat": -17.2237418, "lon": 145.9166465}, {"type": "node", "id": 31207863, "lat": -17.2247716, "lon": 145.9172507}, {"type": "node", "id": 31207865, "lat": -17.2254443, "lon": 145.9176079}, {"type": "node", "id": 31207866, "lat": -17.2260909, "lon": 145.9179448}, {"type": "node", "id": 2113577133, "lat": -17.2182896, "lon": 145.9128549}, {"type": "node", "id": 2113577134, "lat": -17.2270699, "lon": 145.9184521}, {"type": "node", "id": 5780549884, "lat": -17.2081599, "lon": 145.9075314}, {"type": "node", "id": 5780549891, "lat": -17.2054339, "lon": 145.9054251}, {"type": "node", "id": 5780549905, "lat": -17.2241461, "lon": 145.9168893}, {"type": "way", "id": 201389983, "nodes": [2113577133, 31207859, 31207858, 31207857, 31207856, 31207855, 31207854, 31207852, 5780549884, 31207851, 31207850, 31207849, 5780549891], "tags": {"highway": "trunk", "maxspeed": "100", "name": "Bruce Highway", "network": "AU:QLD", "ref": "A1", "source": "survey", "surface": "asphalt"}}, {"type": "way", "id": 201390010, "nodes": [2113577134, 31207866, 31207865, 31207863, 5780549905, 31207862, 31207861, 31207860, 2113577133], "tags": {"highway": "trunk", "maxspeed": "80", "name": "Bruce Highway", "network": "AU:QLD", "ref": "A1", "source": "survey", "surface": "asphalt"}}]}